cadcdata/__init__.py
cadcdata/core.py
cadcdata/storageinv.py
cadcdata/version.py
cadcdata/data/VOSpace-2.0.xsd
cadcdata/data/VOSpace-2.1.xsd
cadcdata-2.5.2.dist-info/licenses/LICENSE
cadcdata-2.5.2.dist-info/METADATA
cadcdata-2.5.2.dist-info/WHEEL
cadcdata-2.5.2.dist-info/entry_points.txt
cadcdata-2.5.2.dist-info/top_level.txt
cadcdata-2.5.2.dist-info/RECORD
