Metadata-Version: 2.4
Name: cadcdata
Version: 2.5.2
Summary: Client for accessing data at the Canadian Astronomy Data Centre
Home-page: http://www.cadc-ccda.hia-iha.nrc-cnrc.gc.ca/data
Author: Canadian Astronomy Data Centre
Author-email: cadc@nrc-cnrc.gc.ca
License: AGPLv3
Classifier: Natural Language :: English
Classifier: License :: OSI Approved :: GNU Affero General Public License v3
Classifier: Programming Language :: Python
Classifier: Programming Language :: Python :: 3
Requires-Python: >=3.7, <4
License-File: LICENSE
Requires-Dist: cadcutils>=1.5.1
Requires-Dist: clint>=0.5.1
Requires-Dist: python-magic>=0.4.15
Requires-Dist: termcolor>=1.1.0
Provides-Extra: test
Requires-Dist: pytest; extra == "test"
Requires-Dist: pytest-cov>=2.5.1; extra == "test"
Requires-Dist: flake8>=3.4.1; extra == "test"
Requires-Dist: funcsigs==1.0.2; extra == "test"
Requires-Dist: xml-compare>=1.0.5; extra == "test"
Dynamic: author
Dynamic: author-email
Dynamic: classifier
Dynamic: description
Dynamic: home-page
Dynamic: license
Dynamic: license-file
Dynamic: requires-python
Dynamic: summary
